gin_train
