Metadata-Version: 2.1
Name: gin-train
Version: 0.1.6
Summary: gin-train: model training boilerplate
Home-page: https://github.com/avsecz/gin-train
Author: Ziga Avsec
Author-email: avsec@in.tum.de
License: MIT license
Keywords: deep learning
Platform: UNKNOWN
Provides-Extra: develop
